pyrobustfs/__init__.py
pyrobustfs/selectors.py
pyrobustfs-0.1.1.dist-info/licenses/LICENSE
pyrobustfs-0.1.1.dist-info/METADATA
pyrobustfs-0.1.1.dist-info/WHEEL
pyrobustfs-0.1.1.dist-info/top_level.txt
pyrobustfs-0.1.1.dist-info/RECORD
