Metadata-Version: 2.4
Name: pyrobustfs
Version: 0.1.1
Summary: A robust feature selection library using ensemble mRMR and optional refinement.
Home-page: https://github.com/manojkumar010/pyrobustfs
Author: Manoj Kumar
Author-email: manojkumar.du.or.21@gmail.com
Classifier: Programming Language :: Python :: 3
Classifier: License :: OSI Approved :: MIT License
Classifier: Operating System :: OS Independent
Classifier: Intended Audience :: Science/Research
Classifier: Topic :: Scientific/Engineering :: Artificial Intelligence
Classifier: Topic :: Scientific/Engineering :: Information Analysis
Requires-Python: >=3.7
License-File: LICENSE
Requires-Dist: pandas>=1.0.0
Requires-Dist: numpy>=1.18.0
Requires-Dist: scikit-learn>=0.23.0
Requires-Dist: feature-engine>=1.0.0
Dynamic: author
Dynamic: author-email
Dynamic: classifier
Dynamic: description
Dynamic: description-content-type
Dynamic: home-page
Dynamic: license-file
Dynamic: requires-dist
Dynamic: requires-python
Dynamic: summary
